trustedflow/attestation/verification/verifier.cpython-310-x86_64-linux-gnu.so
trustedflow_verification-0.3.0.dev20240722.dist-info/LICENSE
trustedflow_verification-0.3.0.dev20240722.dist-info/METADATA
trustedflow_verification-0.3.0.dev20240722.dist-info/WHEEL
trustedflow_verification-0.3.0.dev20240722.dist-info/top_level.txt
trustedflow_verification-0.3.0.dev20240722.dist-info/RECORD
