Metadata-Version: 2.1
Name: trustedflow-verification
Version: 0.3.0.dev20240722
Summary: An attestation report verification library
Home-page: https://github.com/secretflow/trustedflow
Author: secretflow
Author-email: secretflow-contact@service.alipay.com
License: Apache 2.0
Classifier: Programming Language :: Python :: 3
Classifier: License :: OSI Approved :: Apache Software License
Classifier: Operating System :: POSIX :: Linux
License-File: LICENSE
Requires-Dist: protobuf <5.0dev,>=4.21.3
Requires-Dist: sdc-apis ==0.2.1.dev20240320
